upagekite/__init__.py
upagekite/__main__.py
upagekite/captive.py
upagekite/esp32_bootstrap.py
upagekite/esp32_install.py
upagekite/httpd.py
upagekite/proto.py
upagekite/proxy.py
upagekite/web.py
upagekite/web_mpfd.py
upagekite/websocket.py
upagekite/xml_gen.py
upagekite-0.3.2.dist-info/COPYING.txt
upagekite-0.3.2.dist-info/LICENSE.txt
upagekite-0.3.2.dist-info/METADATA
upagekite-0.3.2.dist-info/WHEEL
upagekite-0.3.2.dist-info/top_level.txt
upagekite-0.3.2.dist-info/RECORD
