Metadata-Version: 2.1
Name: upagekite
Version: 0.3.2
Summary: Embeddable/IoT PageKite asyncio web server and framework
Home-page: https://github.com/pagekite/upagekite
Author: Bjarni R. Einarsson
Author-email: bre@pagekite.net
License: GPL-3.0
Download-URL: https://codeload.github.com/pagekite/upagekite/tar.gz/refs/tags/v0.3.2u
Keywords: pagekite,http,websocket,esp32,micropython
Platform: UNKNOWN
Classifier: Development Status :: 3 - Alpha
Classifier: Intended Audience :: Developers
Classifier: License :: OSI Approved :: GNU General Public License v3 or later (GPLv3+)
Classifier: License :: Other/Proprietary License
Classifier: Framework :: AsyncIO
Classifier: Programming Language :: Python :: 3
Classifier: Programming Language :: Python :: Implementation :: CPython
Classifier: Programming Language :: Python :: Implementation :: MicroPython
Classifier: Topic :: Software Development :: Embedded Systems
Classifier: Topic :: Software Development :: Libraries :: Python Modules
Classifier: Topic :: Software Development :: Libraries :: Application Frameworks
Classifier: Topic :: Internet :: WWW/HTTP :: Dynamic Content
Classifier: Topic :: Internet :: WWW/HTTP :: HTTP Servers
